snake_game/__init__.py
snake_game/game.py
snake_game/game_ui.py
snake_game/main.py
play_snake-0.0.2.dist-info/METADATA
play_snake-0.0.2.dist-info/WHEEL
play_snake-0.0.2.dist-info/entry_points.txt
play_snake-0.0.2.dist-info/top_level.txt
play_snake-0.0.2.dist-info/RECORD
